<?xml version="1.0" encoding="UTF-8" standalone="yes"?>
<imgdir name="Voice7.img">
<imgdir name="karotte">
<imgdir name="0A">
<sound name="0"/>
<sound name="1"/>
</imgdir>
<imgdir name="0">
<sound name="0"/>
<sound name="1"/>
<sound name="2"/>
<sound name="3"/>
<sound name="4"/>
<sound name="5"/>
<sound name="6"/>
<sound name="7"/>
<sound name="8"/>
<sound name="9"/>
<sound name="10"/>
<sound name="11"/>
<sound name="12"/>
<sound name="13"/>
<sound name="14"/>
</imgdir>
<imgdir name="1A">
<sound name="0"/>
<sound name="1"/>
<sound name="2"/>
<sound name="3"/>
<sound name="4"/>
<sound name="5"/>
<sound name="6"/>
</imgdir>
<imgdir name="1">
<sound name="0"/>
<sound name="1"/>
<sound name="2"/>
<sound name="3"/>
<sound name="4"/>
<sound name="5"/>
<sound name="6"/>
<sound name="7"/>
<sound name="8"/>
<sound name="9"/>
<sound name="10"/>
<sound name="11"/>
<sound name="12"/>
<sound name="13"/>
</imgdir>
<imgdir name="2A">
<sound name="0"/>
<sound name="1"/>
</imgdir>
<imgdir name="2">
<sound name="0"/>
<sound name="1"/>
<sound name="2"/>
<sound name="3"/>
<sound name="4"/>
<sound name="5"/>
<sound name="6"/>
<sound name="7"/>
<sound name="8"/>
<sound name="9"/>
<sound name="10"/>
<sound name="11"/>
<sound name="12"/>
<sound name="13"/>
<sound name="14"/>
<sound name="15"/>
</imgdir>
<imgdir name="3">
<sound name="0"/>
<sound name="1"/>
<sound name="2"/>
<sound name="3"/>
<sound name="4"/>
<sound name="5"/>
<sound name="6"/>
</imgdir>
<imgdir name="4A">
<sound name="0"/>
<sound name="1"/>
<sound name="2"/>
<sound name="3"/>
<sound name="4"/>
<sound name="5"/>
</imgdir>
<imgdir name="4">
<sound name="0"/>
<sound name="1"/>
<sound name="2"/>
<sound name="3"/>
<sound name="4"/>
<sound name="5"/>
<sound name="6"/>
<sound name="7"/>
<sound name="8"/>
<sound name="9"/>
<sound name="10"/>
<sound name="11"/>
<sound name="12"/>
</imgdir>
<imgdir name="5">
<sound name="0"/>
<sound name="1"/>
<sound name="2"/>
<sound name="3"/>
<sound name="4"/>
<sound name="5"/>
<sound name="6"/>
<sound name="7"/>
<sound name="8"/>
<sound name="9"/>
<sound name="10"/>
<sound name="11"/>
<sound name="12"/>
<sound name="13"/>
<sound name="14"/>
<sound name="15"/>
<sound name="16"/>
<sound name="17"/>
</imgdir>
<imgdir name="6">
<sound name="0"/>
<sound name="1"/>
<sound name="2"/>
<sound name="3"/>
<sound name="4"/>
<sound name="5"/>
<sound name="6"/>
<sound name="7"/>
<sound name="8"/>
<sound name="9"/>
<sound name="10"/>
<sound name="11"/>
<sound name="12"/>
<sound name="13"/>
<sound name="14"/>
<sound name="15"/>
<sound name="16"/>
<sound name="17"/>
<sound name="18"/>
<sound name="19"/>
<sound name="20"/>
</imgdir>
<imgdir name="7A">
<sound name="0"/>
<sound name="1"/>
<sound name="2"/>
<sound name="3"/>
<sound name="4"/>
<sound name="5"/>
<sound name="6"/>
<sound name="7"/>
<sound name="8"/>
<sound name="9"/>
<sound name="10"/>
<sound name="11"/>
<sound name="12"/>
</imgdir>
<imgdir name="7">
<sound name="0"/>
<sound name="1"/>
<sound name="2"/>
<sound name="3"/>
<sound name="4"/>
<sound name="5"/>
<sound name="6"/>
<sound name="7"/>
<sound name="8"/>
<sound name="9"/>
<sound name="10"/>
<sound name="11"/>
<sound name="12"/>
<sound name="13"/>
<sound name="14"/>
<sound name="15"/>
<sound name="16"/>
<sound name="17"/>
<sound name="18"/>
<sound name="19"/>
<sound name="20"/>
<sound name="21"/>
<sound name="22"/>
<sound name="23"/>
<sound name="24"/>
<sound name="25"/>
<sound name="26"/>
<sound name="27"/>
<sound name="28"/>
<sound name="29"/>
<sound name="30"/>
<sound name="31"/>
<sound name="32"/>
<sound name="33"/>
<sound name="34"/>
<sound name="35"/>
<sound name="36"/>
<sound name="37"/>
<sound name="38"/>
<sound name="39"/>
<sound name="40"/>
<sound name="41"/>
<sound name="42"/>
<sound name="43"/>
<sound name="44"/>
<sound name="45"/>
<sound name="46"/>
<sound name="47"/>
<sound name="48"/>
<sound name="49"/>
<sound name="50"/>
</imgdir>
<imgdir name="8A">
<sound name="0"/>
<sound name="1"/>
<sound name="2"/>
<sound name="3"/>
<sound name="4"/>
<sound name="5"/>
<sound name="6"/>
<sound name="7"/>
<sound name="8"/>
<sound name="9"/>
<sound name="10"/>
<sound name="11"/>
<sound name="12"/>
<sound name="13"/>
<sound name="14"/>
<sound name="15"/>
<sound name="16"/>
<sound name="17"/>
<sound name="18"/>
<sound name="19"/>
<sound name="20"/>
</imgdir>
<imgdir name="8">
<sound name="0"/>
<sound name="1"/>
<sound name="2"/>
<sound name="3"/>
<sound name="4"/>
<sound name="5"/>
<sound name="6"/>
<sound name="7"/>
<sound name="8"/>
<sound name="9"/>
<sound name="10"/>
<sound name="11"/>
<sound name="12"/>
<sound name="13"/>
<sound name="14"/>
<sound name="15"/>
<sound name="16"/>
<sound name="17"/>
<sound name="18"/>
<sound name="19"/>
<sound name="20"/>
<sound name="21"/>
<sound name="22"/>
<sound name="23"/>
<sound name="24"/>
<sound name="25"/>
</imgdir>
<imgdir name="9A">
<sound name="0"/>
<sound name="1"/>
<sound name="2"/>
<sound name="3"/>
<sound name="4"/>
<sound name="5"/>
</imgdir>
<imgdir name="9">
<sound name="0"/>
<sound name="1"/>
<sound name="2"/>
<sound name="3"/>
<sound name="4"/>
<sound name="5"/>
<sound name="6"/>
<sound name="7"/>
<sound name="8"/>
<sound name="9"/>
<sound name="10"/>
<sound name="11"/>
<sound name="12"/>
<sound name="13"/>
<sound name="14"/>
</imgdir>
</imgdir>
<imgdir name="arcs">
<imgdir name="0">
<sound name="0"/>
<sound name="1"/>
<sound name="2"/>
<sound name="3"/>
<sound name="4"/>
<sound name="5"/>
<sound name="6"/>
<sound name="7"/>
<sound name="8"/>
<sound name="9"/>
<sound name="10"/>
<sound name="11"/>
<sound name="12"/>
<sound name="13"/>
<sound name="14"/>
<sound name="15"/>
<sound name="16"/>
<sound name="17"/>
<sound name="18"/>
<sound name="19"/>
<sound name="20"/>
<sound name="21"/>
<sound name="22"/>
<sound name="23"/>
<sound name="24"/>
<sound name="25"/>
<sound name="26"/>
<sound name="27"/>
</imgdir>
<imgdir name="1">
<sound name="0"/>
<sound name="1"/>
<sound name="2"/>
<sound name="3"/>
<sound name="4"/>
<sound name="5"/>
<sound name="6"/>
</imgdir>
<imgdir name="2">
<sound name="0"/>
<sound name="1"/>
<sound name="2"/>
<sound name="3"/>
<sound name="4"/>
<sound name="5"/>
<sound name="6"/>
<sound name="7"/>
<sound name="8"/>
<sound name="9"/>
<sound name="10"/>
<sound name="11"/>
<sound name="12"/>
<sound name="13"/>
<sound name="14"/>
<sound name="15"/>
<sound name="16"/>
<sound name="17"/>
<sound name="18"/>
<sound name="19"/>
<sound name="20"/>
<sound name="21"/>
<sound name="22"/>
<sound name="23"/>
<sound name="24"/>
<sound name="25"/>
<sound name="26"/>
<sound name="27"/>
</imgdir>
<imgdir name="3">
<sound name="0"/>
<sound name="1"/>
<sound name="2"/>
<sound name="3"/>
<sound name="4"/>
<sound name="5"/>
</imgdir>
<imgdir name="4">
<sound name="0"/>
<sound name="1"/>
<sound name="2"/>
<sound name="3"/>
<sound name="4"/>
<sound name="5"/>
</imgdir>
<imgdir name="5">
<sound name="0"/>
<sound name="1"/>
<sound name="2"/>
<sound name="3"/>
<sound name="4"/>
<sound name="5"/>
<sound name="6"/>
<sound name="7"/>
<sound name="8"/>
<sound name="9"/>
<sound name="10"/>
<sound name="11"/>
<sound name="12"/>
<sound name="13"/>
<sound name="14"/>
<sound name="15"/>
<sound name="16"/>
<sound name="17"/>
<sound name="18"/>
<sound name="19"/>
<sound name="20"/>
<sound name="21"/>
<sound name="22"/>
<sound name="23"/>
<sound name="24"/>
<sound name="25"/>
<sound name="26"/>
<sound name="27"/>
<sound name="28"/>
<sound name="29"/>
<sound name="30"/>
<sound name="31"/>
<sound name="32"/>
<sound name="33"/>
<sound name="34"/>
<sound name="35"/>
<sound name="36"/>
<sound name="37"/>
<sound name="38"/>
</imgdir>
<imgdir name="6">
<sound name="0"/>
<sound name="1"/>
<sound name="2"/>
<sound name="3"/>
<sound name="4"/>
<sound name="5"/>
<sound name="6"/>
<sound name="7"/>
<sound name="8"/>
<sound name="9"/>
<sound name="10"/>
<sound name="11"/>
<sound name="12"/>
<sound name="13"/>
<sound name="14"/>
</imgdir>
<imgdir name="7">
<sound name="0"/>
<sound name="1"/>
<sound name="2"/>
<sound name="3"/>
<sound name="4"/>
<sound name="5"/>
<sound name="6"/>
<sound name="7"/>
<sound name="8"/>
<sound name="9"/>
<sound name="10"/>
<sound name="11"/>
<sound name="12"/>
<sound name="13"/>
<sound name="14"/>
<sound name="15"/>
<sound name="16"/>
<sound name="17"/>
<sound name="18"/>
<sound name="19"/>
<sound name="20"/>
<sound name="21"/>
<sound name="22"/>
<sound name="23"/>
<sound name="24"/>
<sound name="25"/>
<sound name="26"/>
<sound name="27"/>
<sound name="28"/>
<sound name="29"/>
<sound name="30"/>
<sound name="31"/>
<sound name="32"/>
<sound name="33"/>
<sound name="34"/>
<sound name="35"/>
<sound name="36"/>
</imgdir>
<imgdir name="8">
<sound name="0"/>
<sound name="1"/>
<sound name="2"/>
<sound name="3"/>
<sound name="4"/>
<sound name="5"/>
<sound name="6"/>
<sound name="7"/>
<sound name="8"/>
<sound name="9"/>
<sound name="10"/>
<sound name="11"/>
<sound name="12"/>
<sound name="13"/>
<sound name="14"/>
<sound name="15"/>
<sound name="16"/>
<sound name="17"/>
<sound name="18"/>
<sound name="19"/>
<sound name="20"/>
<sound name="21"/>
<sound name="22"/>
<sound name="23"/>
<sound name="24"/>
<sound name="25"/>
<sound name="26"/>
<sound name="27"/>
<sound name="28"/>
<sound name="29"/>
</imgdir>
<imgdir name="9">
<sound name="0"/>
<sound name="1"/>
<sound name="2"/>
<sound name="3"/>
<sound name="4"/>
<sound name="5"/>
<sound name="6"/>
<sound name="7"/>
<sound name="8"/>
<sound name="9"/>
<sound name="10"/>
<sound name="11"/>
<sound name="12"/>
<sound name="13"/>
<sound name="14"/>
<sound name="15"/>
<sound name="16"/>
<sound name="17"/>
<sound name="18"/>
<sound name="19"/>
<sound name="20"/>
<sound name="21"/>
<sound name="22"/>
<sound name="23"/>
</imgdir>
<imgdir name="10">
<sound name="0"/>
<sound name="1"/>
<sound name="2"/>
<sound name="3"/>
<sound name="4"/>
<sound name="5"/>
<sound name="6"/>
<sound name="7"/>
<sound name="8"/>
<sound name="9"/>
<sound name="10"/>
<sound name="11"/>
<sound name="12"/>
<sound name="13"/>
<sound name="14"/>
<sound name="15"/>
<sound name="16"/>
<sound name="17"/>
<sound name="18"/>
<sound name="19"/>
<sound name="20"/>
<sound name="21"/>
</imgdir>
</imgdir>
<imgdir name="cygnus2022">
<imgdir name="1">
<sound name="1"/>
<sound name="2"/>
<sound name="3"/>
<sound name="4"/>
<sound name="5"/>
<sound name="6"/>
<sound name="7"/>
<sound name="13"/>
<sound name="14"/>
<sound name="15"/>
</imgdir>
<imgdir name="2">
<sound name="1"/>
<sound name="3"/>
<sound name="5"/>
<sound name="6"/>
<sound name="7"/>
<sound name="9"/>
<sound name="10"/>
<sound name="12"/>
<sound name="13"/>
<sound name="15"/>
<sound name="17"/>
<sound name="18"/>
<sound name="20"/>
</imgdir>
<imgdir name="3">
<sound name="1"/>
<sound name="2"/>
<sound name="3"/>
<sound name="4"/>
<sound name="5"/>
<sound name="6"/>
<sound name="7"/>
<sound name="8"/>
<sound name="9"/>
<sound name="10"/>
<sound name="13"/>
<sound name="14"/>
<sound name="15"/>
<sound name="16"/>
<sound name="19"/>
<sound name="21"/>
<sound name="22"/>
<sound name="23-1"/>
<sound name="23-2"/>
<sound name="24"/>
<sound name="25"/>
<sound name="26"/>
<sound name="28"/>
<sound name="29"/>
<sound name="30"/>
</imgdir>
<imgdir name="4">
<sound name="1"/>
<sound name="2"/>
<sound name="3"/>
<sound name="4"/>
<sound name="5"/>
<sound name="7"/>
<sound name="8"/>
<sound name="9"/>
<sound name="11"/>
<sound name="12"/>
<sound name="13"/>
<sound name="14"/>
<sound name="15"/>
</imgdir>
<imgdir name="5">
<sound name="1"/>
<sound name="3"/>
<sound name="4"/>
<sound name="6"/>
<sound name="7"/>
<sound name="9"/>
<sound name="10"/>
<sound name="12"/>
<sound name="14"/>
<sound name="16"/>
<sound name="18"/>
<sound name="19"/>
<sound name="21"/>
<sound name="22"/>
<sound name="24"/>
<sound name="26"/>
<sound name="27"/>
<sound name="28"/>
<sound name="30"/>
<sound name="32"/>
<sound name="34"/>
<sound name="35"/>
<sound name="37"/>
<sound name="39"/>
<sound name="40"/>
<sound name="42"/>
<sound name="44"/>
<sound name="46"/>
<sound name="47"/>
</imgdir>
<imgdir name="6">
<sound name="1"/>
<sound name="2"/>
<sound name="3"/>
<sound name="4"/>
<sound name="5"/>
<sound name="6"/>
<sound name="7"/>
<sound name="8"/>
<sound name="9"/>
<sound name="10"/>
<sound name="11"/>
<sound name="12"/>
<sound name="13"/>
<sound name="14"/>
<sound name="15"/>
<sound name="16"/>
<sound name="17"/>
<sound name="18"/>
<sound name="19"/>
<sound name="20"/>
</imgdir>
<imgdir name="7">
<sound name="1"/>
<sound name="2"/>
<sound name="3"/>
<sound name="4"/>
<sound name="5"/>
<sound name="6"/>
<sound name="7"/>
<sound name="8"/>
<sound name="9"/>
<sound name="10"/>
<sound name="11"/>
<sound name="12"/>
<sound name="13"/>
<sound name="14"/>
<sound name="15"/>
<sound name="16"/>
<sound name="17"/>
<sound name="18"/>
<sound name="19"/>
<sound name="20"/>
<sound name="21"/>
</imgdir>
<imgdir name="8">
<sound name="1"/>
<sound name="2"/>
<sound name="3"/>
<sound name="4"/>
<sound name="5"/>
<sound name="6"/>
<sound name="7"/>
<sound name="8"/>
<sound name="9"/>
<sound name="10"/>
<sound name="11"/>
<sound name="12"/>
<sound name="13"/>
<sound name="14"/>
<sound name="15"/>
<sound name="16"/>
<sound name="17"/>
<sound name="18"/>
<sound name="19"/>
<sound name="20"/>
<sound name="21"/>
</imgdir>
<imgdir name="9">
<sound name="1"/>
<sound name="2"/>
<sound name="2-1"/>
<sound name="3"/>
<sound name="4"/>
<sound name="5"/>
<sound name="6"/>
<sound name="7"/>
<sound name="8"/>
<sound name="9"/>
<sound name="10"/>
<sound name="11"/>
<sound name="12"/>
<sound name="13"/>
<sound name="14"/>
<sound name="15"/>
<sound name="16"/>
<sound name="17"/>
<sound name="18"/>
<sound name="19"/>
<sound name="20"/>
<sound name="21"/>
<sound name="22"/>
<sound name="23"/>
</imgdir>
<imgdir name="10">
<sound name="2"/>
<sound name="3"/>
<sound name="4"/>
<sound name="5"/>
<sound name="6"/>
<sound name="7"/>
<sound name="8"/>
<sound name="11"/>
<sound name="12"/>
<sound name="13"/>
<sound name="14"/>
<sound name="16"/>
<sound name="17"/>
<sound name="19"/>
<sound name="20"/>
<sound name="21"/>
</imgdir>
<imgdir name="11">
<sound name="1"/>
<sound name="2"/>
<sound name="3"/>
<sound name="4"/>
<sound name="5"/>
<sound name="6"/>
<sound name="7"/>
<sound name="9"/>
<sound name="10"/>
</imgdir>
<imgdir name="12">
<sound name="1"/>
<sound name="3"/>
<sound name="4"/>
<sound name="5"/>
<sound name="6"/>
<sound name="7"/>
<sound name="8"/>
<sound name="9"/>
<sound name="10"/>
<sound name="11"/>
<sound name="13"/>
<sound name="16"/>
<sound name="17"/>
<sound name="19"/>
<sound name="20"/>
<sound name="21"/>
<sound name="22"/>
<sound name="23"/>
<sound name="24"/>
<sound name="25"/>
<sound name="26"/>
<sound name="27"/>
<sound name="28"/>
<sound name="29"/>
<sound name="30"/>
<sound name="31"/>
<sound name="32"/>
<sound name="33"/>
</imgdir>
<imgdir name="14">
<sound name="1"/>
<sound name="3"/>
<sound name="5"/>
<sound name="7"/>
<sound name="9"/>
<sound name="11"/>
<sound name="14"/>
<sound name="15"/>
</imgdir>
<imgdir name="15">
<sound name="1"/>
<sound name="3"/>
<sound name="4"/>
<sound name="5"/>
<sound name="7"/>
<sound name="8"/>
<sound name="10"/>
<sound name="11"/>
<sound name="12"/>
<sound name="14"/>
<sound name="15"/>
<sound name="17"/>
<sound name="18"/>
<sound name="20"/>
<sound name="22"/>
<sound name="23"/>
<sound name="24"/>
<sound name="25"/>
<sound name="26"/>
<sound name="27"/>
<sound name="28"/>
<sound name="29"/>
<sound name="30"/>
<sound name="31"/>
</imgdir>
<imgdir name="16">
<sound name="1"/>
<sound name="3"/>
<sound name="6"/>
<sound name="7"/>
<sound name="10"/>
<sound name="11"/>
<sound name="13"/>
<sound name="14"/>
<sound name="16"/>
<sound name="17"/>
<sound name="19"/>
<sound name="20"/>
<sound name="21"/>
<sound name="23"/>
<sound name="24"/>
<sound name="26"/>
<sound name="27"/>
<sound name="29"/>
<sound name="30"/>
<sound name="31"/>
<sound name="33"/>
<sound name="34"/>
<sound name="36"/>
<sound name="38"/>
<sound name="39"/>
<sound name="41"/>
<sound name="42"/>
<sound name="44"/>
<sound name="45"/>
<sound name="47"/>
<sound name="49"/>
<sound name="50"/>
<sound name="51"/>
<sound name="53"/>
</imgdir>
<imgdir name="17">
<sound name="1"/>
<sound name="3"/>
<sound name="4"/>
<sound name="5"/>
<sound name="7"/>
<sound name="8"/>
<sound name="9"/>
<sound name="10"/>
</imgdir>
<imgdir name="18">
<sound name="1"/>
<sound name="3"/>
<sound name="4"/>
<sound name="5"/>
<sound name="6"/>
<sound name="8"/>
<sound name="9"/>
</imgdir>
<imgdir name="19">
<sound name="1"/>
<sound name="2"/>
<sound name="3"/>
<sound name="4"/>
<sound name="5"/>
<sound name="6"/>
</imgdir>
<imgdir name="20">
<sound name="1"/>
<sound name="3"/>
<sound name="5"/>
<sound name="6"/>
<sound name="8"/>
<sound name="9"/>
<sound name="10"/>
<sound name="11"/>
<sound name="13"/>
<sound name="14"/>
<sound name="16"/>
<sound name="18"/>
<sound name="19"/>
<sound name="20"/>
<sound name="22"/>
<sound name="23"/>
<sound name="24"/>
<sound name="26"/>
<sound name="27"/>
<sound name="29"/>
<sound name="30"/>
<sound name="31"/>
<sound name="33"/>
<sound name="35"/>
<sound name="36"/>
<sound name="37"/>
<sound name="38"/>
<sound name="40"/>
<sound name="41"/>
<sound name="42"/>
<sound name="44"/>
<sound name="45"/>
<sound name="46"/>
<sound name="48"/>
<sound name="49"/>
<sound name="51"/>
</imgdir>
</imgdir>
<imgdir name="mikhail2022">
<imgdir name="1">
<sound name="1"/>
<sound name="2"/>
<sound name="3"/>
<sound name="4"/>
<sound name="5"/>
<sound name="6"/>
<sound name="7"/>
<sound name="8"/>
<sound name="9"/>
<sound name="10"/>
<sound name="11"/>
<sound name="12"/>
<sound name="13"/>
<sound name="14"/>
<sound name="15"/>
<sound name="16"/>
<sound name="17"/>
<sound name="18"/>
<sound name="19"/>
<sound name="20"/>
<sound name="21"/>
<sound name="22"/>
<sound name="23"/>
<sound name="24"/>
<sound name="25"/>
<sound name="26"/>
<sound name="27"/>
<sound name="28"/>
<sound name="29"/>
</imgdir>
<imgdir name="2">
<sound name="1"/>
<sound name="2"/>
<sound name="3"/>
<sound name="4"/>
<sound name="5"/>
<sound name="6"/>
<sound name="7"/>
<sound name="8"/>
<sound name="9"/>
<sound name="10"/>
<sound name="11"/>
<sound name="12"/>
<sound name="13"/>
<sound name="14"/>
<sound name="15"/>
</imgdir>
<imgdir name="6">
<sound name="1"/>
<sound name="2"/>
<sound name="3"/>
<sound name="4"/>
<sound name="5"/>
<sound name="6"/>
<sound name="7"/>
<sound name="8"/>
<sound name="9"/>
<sound name="10"/>
<sound name="11"/>
<sound name="12"/>
<sound name="13"/>
<sound name="14"/>
<sound name="15"/>
<sound name="16"/>
<sound name="17"/>
<sound name="18"/>
<sound name="19"/>
<sound name="20"/>
<sound name="21"/>
<sound name="22"/>
</imgdir>
<imgdir name="8">
<sound name="3"/>
<sound name="4"/>
</imgdir>
<imgdir name="9">
<sound name="1"/>
<sound name="2"/>
<sound name="3"/>
<sound name="4"/>
<sound name="5"/>
<sound name="6"/>
<sound name="7"/>
<sound name="8"/>
<sound name="9"/>
<sound name="11"/>
<sound name="12"/>
<sound name="13"/>
<sound name="14"/>
</imgdir>
<imgdir name="10">
<sound name="1"/>
<sound name="2"/>
<sound name="3"/>
<sound name="4"/>
<sound name="5"/>
<sound name="6"/>
<sound name="7"/>
<sound name="11"/>
<sound name="12"/>
<sound name="13"/>
<sound name="14"/>
<sound name="15"/>
</imgdir>
<imgdir name="11">
<sound name="1"/>
<sound name="2"/>
<sound name="3"/>
<sound name="4"/>
<sound name="5"/>
<sound name="6"/>
<sound name="7"/>
<sound name="8"/>
<sound name="9"/>
<sound name="10"/>
<sound name="11"/>
<sound name="12"/>
<sound name="13"/>
<sound name="14"/>
<sound name="15"/>
<sound name="16"/>
<sound name="17"/>
<sound name="18"/>
<sound name="19"/>
<sound name="20"/>
<sound name="21"/>
<sound name="22"/>
<sound name="23"/>
<sound name="24"/>
<sound name="25"/>
<sound name="26"/>
<sound name="27"/>
<sound name="28"/>
<sound name="29"/>
<sound name="30"/>
</imgdir>
<imgdir name="12">
<sound name="11"/>
<sound name="13"/>
<sound name="16"/>
<sound name="17"/>
<sound name="19"/>
<sound name="20"/>
<sound name="21"/>
<sound name="22"/>
<sound name="23"/>
<sound name="24"/>
<sound name="25"/>
<sound name="26"/>
<sound name="27"/>
<sound name="28"/>
<sound name="29"/>
<sound name="30"/>
<sound name="31"/>
<sound name="32"/>
<sound name="33"/>
</imgdir>
<imgdir name="14">
<sound name="1"/>
<sound name="2"/>
<sound name="3"/>
<sound name="4"/>
<sound name="6"/>
<sound name="8"/>
<sound name="9"/>
<sound name="11"/>
<sound name="13"/>
<sound name="14"/>
<sound name="15"/>
<sound name="16"/>
<sound name="17"/>
<sound name="18"/>
<sound name="19"/>
<sound name="20"/>
<sound name="21"/>
<sound name="22"/>
<sound name="23"/>
<sound name="24"/>
<sound name="25"/>
<sound name="26"/>
<sound name="27"/>
<sound name="28"/>
</imgdir>
<imgdir name="15">
<sound name="1"/>
<sound name="2"/>
<sound name="3"/>
<sound name="4"/>
<sound name="5"/>
<sound name="6"/>
<sound name="7"/>
<sound name="8"/>
<sound name="9"/>
<sound name="10"/>
<sound name="11"/>
<sound name="12"/>
<sound name="13"/>
<sound name="14"/>
<sound name="15"/>
<sound name="16"/>
<sound name="17"/>
<sound name="18"/>
<sound name="19"/>
<sound name="20"/>
<sound name="21"/>
<sound name="22"/>
<sound name="23"/>
<sound name="24"/>
</imgdir>
<imgdir name="16">
<sound name="1"/>
<sound name="2"/>
<sound name="3"/>
<sound name="4"/>
<sound name="5"/>
<sound name="6"/>
<sound name="7"/>
<sound name="8"/>
<sound name="9"/>
<sound name="10"/>
<sound name="11"/>
<sound name="12"/>
<sound name="13"/>
<sound name="14"/>
<sound name="15"/>
<sound name="16"/>
<sound name="17"/>
<sound name="18"/>
<sound name="19"/>
<sound name="20"/>
<sound name="21"/>
</imgdir>
<imgdir name="17">
<sound name="1"/>
<sound name="2"/>
<sound name="3"/>
<sound name="4"/>
<sound name="5"/>
<sound name="6"/>
<sound name="7"/>
<sound name="8"/>
<sound name="9"/>
<sound name="10"/>
<sound name="11"/>
<sound name="12"/>
<sound name="13"/>
<sound name="14"/>
<sound name="15"/>
<sound name="16"/>
<sound name="17"/>
<sound name="18"/>
<sound name="19"/>
</imgdir>
<imgdir name="18">
<sound name="1"/>
<sound name="2"/>
<sound name="3"/>
<sound name="4"/>
<sound name="5"/>
<sound name="6"/>
<sound name="7"/>
<sound name="8"/>
<sound name="9"/>
<sound name="10"/>
<sound name="11"/>
<sound name="13"/>
<sound name="12"/>
</imgdir>
<imgdir name="19">
<sound name="1"/>
<sound name="2"/>
<sound name="3"/>
<sound name="4"/>
<sound name="5"/>
<sound name="6"/>
<sound name="8"/>
<sound name="9"/>
<sound name="10"/>
<sound name="11"/>
<sound name="12"/>
<sound name="13"/>
<sound name="14"/>
<sound name="15"/>
<sound name="16"/>
<sound name="17"/>
<sound name="18"/>
<sound name="19"/>
<sound name="20"/>
<sound name="21"/>
<sound name="22"/>
<sound name="23"/>
<sound name="24"/>
<sound name="25"/>
<sound name="26"/>
<sound name="27"/>
<sound name="28"/>
<sound name="29"/>
</imgdir>
<imgdir name="20">
<sound name="1"/>
<sound name="2"/>
<sound name="3"/>
<sound name="4"/>
<sound name="5"/>
<sound name="6"/>
<sound name="7"/>
<sound name="8"/>
<sound name="9"/>
<sound name="10"/>
<sound name="11"/>
<sound name="12-1"/>
<sound name="12-2"/>
<sound name="13"/>
<sound name="14"/>
<sound name="15"/>
<sound name="16"/>
<sound name="17"/>
<sound name="18"/>
<sound name="19"/>
<sound name="20"/>
<sound name="21"/>
<sound name="22"/>
<sound name="23"/>
<sound name="24"/>
<sound name="25"/>
<sound name="26"/>
<sound name="27"/>
<sound name="28"/>
</imgdir>
<imgdir name="21">
<sound name="1"/>
<sound name="2"/>
<sound name="3"/>
<sound name="4"/>
<sound name="5"/>
<sound name="6"/>
<sound name="7"/>
<sound name="8"/>
<sound name="9"/>
<sound name="10"/>
<sound name="11"/>
<sound name="12"/>
<sound name="13"/>
<sound name="14"/>
<sound name="15"/>
<sound name="16"/>
<sound name="17"/>
<sound name="18"/>
<sound name="19"/>
<sound name="20"/>
<sound name="21"/>
<sound name="22"/>
</imgdir>
<imgdir name="22">
<sound name="1"/>
<sound name="2"/>
<sound name="3"/>
<sound name="4"/>
<sound name="5"/>
<sound name="6"/>
</imgdir>
<imgdir name="23">
<sound name="1"/>
<sound name="2"/>
<sound name="3"/>
<sound name="4"/>
<sound name="5"/>
<sound name="6"/>
<sound name="7"/>
<sound name="8"/>
<sound name="9"/>
<sound name="10"/>
<sound name="11"/>
<sound name="12"/>
<sound name="13"/>
<sound name="14"/>
<sound name="15"/>
<sound name="16"/>
<sound name="17"/>
<sound name="18"/>
<sound name="19"/>
<sound name="20"/>
<sound name="21"/>
<sound name="22"/>
<sound name="23"/>
<sound name="24"/>
<sound name="25"/>
<sound name="26"/>
<sound name="27"/>
<sound name="28"/>
<sound name="29"/>
<sound name="30"/>
<sound name="31"/>
<sound name="32"/>
</imgdir>
<imgdir name="24">
<sound name="2"/>
<sound name="3"/>
<sound name="5"/>
<sound name="6"/>
<sound name="7"/>
<sound name="8"/>
<sound name="9"/>
<sound name="10"/>
<sound name="11"/>
<sound name="12"/>
<sound name="15"/>
<sound name="16"/>
<sound name="17"/>
<sound name="18"/>
<sound name="19"/>
<sound name="20"/>
<sound name="21"/>
<sound name="22"/>
</imgdir>
<imgdir name="25">
<sound name="1"/>
<sound name="2"/>
<sound name="3"/>
<sound name="4"/>
<sound name="5"/>
<sound name="6"/>
<sound name="7"/>
<sound name="8"/>
<sound name="9"/>
<sound name="10"/>
<sound name="11"/>
<sound name="12"/>
<sound name="13"/>
<sound name="14"/>
<sound name="15"/>
<sound name="16"/>
<sound name="17"/>
</imgdir>
<imgdir name="26">
<sound name="1"/>
<sound name="2"/>
<sound name="3"/>
<sound name="4"/>
<sound name="5"/>
<sound name="6"/>
<sound name="7"/>
<sound name="8"/>
<sound name="9"/>
<sound name="10"/>
<sound name="11"/>
<sound name="12"/>
<sound name="13"/>
<sound name="14"/>
<sound name="15"/>
<sound name="16"/>
<sound name="17"/>
<sound name="18"/>
<sound name="19"/>
<sound name="20"/>
<sound name="21"/>
<sound name="22"/>
</imgdir>
<imgdir name="27">
<sound name="1"/>
<sound name="2"/>
<sound name="3"/>
<sound name="4"/>
<sound name="5"/>
<sound name="6"/>
<sound name="7"/>
<sound name="8"/>
<sound name="9"/>
<sound name="10"/>
<sound name="11"/>
<sound name="12"/>
<sound name="13"/>
<sound name="14"/>
<sound name="15"/>
<sound name="16"/>
<sound name="17"/>
<sound name="18"/>
<sound name="19"/>
<sound name="20"/>
<sound name="21"/>
<sound name="22"/>
<sound name="23"/>
<sound name="24"/>
<sound name="25"/>
<sound name="26"/>
<sound name="27"/>
<sound name="28"/>
<sound name="29"/>
<sound name="30"/>
<sound name="31"/>
<sound name="32"/>
<sound name="33"/>
<sound name="34"/>
<sound name="35"/>
<sound name="36"/>
</imgdir>
<imgdir name="30">
<sound name="1"/>
<sound name="2"/>
<sound name="3"/>
<sound name="4"/>
<sound name="5"/>
<sound name="6"/>
<sound name="7"/>
<sound name="8"/>
<sound name="9"/>
<sound name="10"/>
<sound name="11"/>
<sound name="12"/>
<sound name="13"/>
<sound name="14"/>
<sound name="15"/>
<sound name="16"/>
</imgdir>
<imgdir name="32">
<sound name="1"/>
<sound name="2"/>
<sound name="3"/>
<sound name="4"/>
<sound name="5"/>
<sound name="6"/>
<sound name="7"/>
<sound name="8"/>
<sound name="9"/>
<sound name="10"/>
<sound name="11"/>
</imgdir>
<imgdir name="33">
<sound name="1"/>
<sound name="2"/>
<sound name="3"/>
<sound name="4"/>
<sound name="5"/>
<sound name="6"/>
<sound name="7"/>
<sound name="8"/>
<sound name="9"/>
<sound name="10"/>
<sound name="11"/>
<sound name="12"/>
<sound name="13"/>
<sound name="14"/>
<sound name="15"/>
<sound name="16"/>
<sound name="17"/>
<sound name="18"/>
<sound name="19"/>
<sound name="20"/>
</imgdir>
<imgdir name="34">
<sound name="1"/>
<sound name="2"/>
<sound name="3"/>
<sound name="4"/>
<sound name="5"/>
<sound name="6"/>
<sound name="7"/>
<sound name="8"/>
<sound name="9"/>
<sound name="10"/>
<sound name="11"/>
<sound name="12"/>
<sound name="13"/>
<sound name="14"/>
</imgdir>
<imgdir name="36">
<sound name="1"/>
<sound name="2"/>
<sound name="3"/>
<sound name="4"/>
<sound name="5"/>
<sound name="6"/>
<sound name="7"/>
<sound name="8"/>
<sound name="9"/>
<sound name="10"/>
<sound name="11"/>
<sound name="12"/>
<sound name="13"/>
<sound name="14"/>
<sound name="16"/>
<sound name="17"/>
</imgdir>
<imgdir name="37">
<sound name="1"/>
<sound name="2"/>
<sound name="3"/>
<sound name="4"/>
<sound name="5"/>
<sound name="6"/>
<sound name="7"/>
<sound name="8"/>
<sound name="9"/>
<sound name="10"/>
<sound name="11"/>
<sound name="12"/>
<sound name="13"/>
<sound name="14"/>
<sound name="15"/>
<sound name="16"/>
<sound name="17"/>
<sound name="18"/>
<sound name="19"/>
<sound name="20"/>
<sound name="21"/>
<sound name="22"/>
<sound name="23"/>
<sound name="24"/>
<sound name="25"/>
<sound name="26"/>
<sound name="27"/>
<sound name="29"/>
<sound name="30"/>
<sound name="31"/>
<sound name="32"/>
<sound name="33"/>
<sound name="34"/>
<sound name="35"/>
<sound name="36"/>
<sound name="37"/>
<sound name="38"/>
<sound name="28"/>
</imgdir>
<imgdir name="38">
<sound name="1"/>
<sound name="2"/>
<sound name="3"/>
<sound name="4"/>
<sound name="5"/>
<sound name="6"/>
<sound name="7"/>
<sound name="8"/>
<sound name="9"/>
</imgdir>
<imgdir name="39">
<sound name="1"/>
<sound name="2"/>
<sound name="7"/>
<sound name="15"/>
</imgdir>
<imgdir name="40">
<sound name="7"/>
<sound name="8"/>
<sound name="10"/>
</imgdir>
<imgdir name="52">
<sound name="1"/>
<sound name="2"/>
<sound name="3"/>
<sound name="4"/>
<sound name="7"/>
<sound name="9"/>
<sound name="14"/>
<sound name="19"/>
<sound name="20"/>
</imgdir>
<imgdir name="53">
<sound name="1"/>
<sound name="2"/>
<sound name="3"/>
<sound name="4"/>
<sound name="5-1"/>
<sound name="5-2"/>
<sound name="6"/>
<sound name="7"/>
<sound name="8"/>
<sound name="9"/>
<sound name="10"/>
<sound name="11"/>
<sound name="12"/>
<sound name="13"/>
<sound name="14"/>
<sound name="15"/>
<sound name="16"/>
<sound name="17"/>
<sound name="18"/>
<sound name="19"/>
<sound name="20"/>
</imgdir>
<imgdir name="54">
<sound name="1"/>
<sound name="2"/>
<sound name="3"/>
<sound name="4"/>
<sound name="5"/>
<sound name="6"/>
<sound name="7"/>
<sound name="7-2"/>
<sound name="8"/>
<sound name="9"/>
<sound name="10"/>
<sound name="11"/>
<sound name="12"/>
<sound name="13"/>
<sound name="14"/>
</imgdir>
</imgdir>
</imgdir>
