<?xml version="1.0" encoding="UTF-8" standalone="yes"?><imgdir name="00060913.img"><imgdir name="info"><string name="islot" value="Hr"/><string name="vslot" value="H1H2H3H4H5H6HfHsHb"/><int name="cash" value="1"/><int name="extendFrame" value="1"/><imgdir name="vehicleDefaultFrame"><int name="jump" value="1"/></imgdir></imgdir><imgdir name="default"><uol name="hairOverHead" value="../stand1/0/hairOverHead"/><uol name="hair" value="../stand1/0/hair"/><uol name="hairBelowBody" value="../stand1/0/hairBelowBody"/><imgdir name="hairShade"><canvas name="0" width="1" height="1"><vector name="origin" x="15" y="12"/><imgdir name="map"><vector name="brow" x="0" y="0"/></imgdir><string name="z" value="hairShade"/><string name="group" value="skin"/><string name="_hash" value="8e1dda4e77000eb6dbc9b84261dc029b81a340502a70a1f7cbbf63f5aecd95af"/><string name="_outlink" value="Character/Hair/00060910.img/default/hairShade/0"/></canvas><uol name="1" value="0"/><uol name="2" value="0"/><uol name="3" value="0"/><uol name="4" value="0"/><uol name="9" value="0"/><uol name="10" value="0"/><uol name="11" value="0"/></imgdir></imgdir><imgdir name="backDefault"><uol name="backHair" value="../ladder/0/backHair"/><uol name="backHairBelowCap" value="../ladder/0/backHairBelowCap"/></imgdir><imgdir name="walk1"><imgdir name="0"><canvas name="hairOverHead" width="55" height="38"><vector name="origin" x="23" y="20"/><imgdir name="map"><vector name="brow" x="0" y="0"/></imgdir><string name="z" value="hairOverHead"/><string name="_hash" value="d8b77064e6b6364777515c4ba357c363ef577557dca0e49c801aeece40c9bcda"/></canvas><canvas name="hair" width="41" height="33"><vector name="origin" x="17" y="15"/><imgdir name="map"><vector name="brow" x="0" y="0"/></imgdir><string name="z" value="hair"/><string name="_hash" value="cfd30a99467f806938955aadc127e26cc47fba7108dab6f097226fd373d01936"/></canvas><canvas name="hairBelowBody" width="46" height="42"><vector name="origin" x="19" y="15"/><imgdir name="map"><vector name="brow" x="0" y="0"/></imgdir><string name="z" value="hairBelowBody"/><string name="_hash" value="4bc53c3ff963b0d250b92fcefd9d54a145d1ce4c9faf2089b8ad55c3a97c804d"/></canvas><uol name="hairShade" value="../../default/hairShade"/></imgdir><imgdir name="1"><canvas name="hairOverHead" width="55" height="38"><vector name="origin" x="23" y="20"/><imgdir name="map"><vector name="brow" x="0" y="0"/></imgdir><string name="z" value="hairOverHead"/><string name="_hash" value="a705f1a1f141e777c7cf55133ef293cbc22dadbcd27f3da2e6d2abcb11642a87"/></canvas><canvas name="hair" width="41" height="33"><vector name="origin" x="17" y="15"/><imgdir name="map"><vector name="brow" x="0" y="0"/></imgdir><string name="z" value="hair"/><string name="_hash" value="334350a569b135ae9cd6df556c45a9bc936f90ca81f1a6e7bbe74b7afe9d91f7"/></canvas><canvas name="hairBelowBody" width="46" height="42"><vector name="origin" x="19" y="15"/><imgdir name="map"><vector name="brow" x="0" y="0"/></imgdir><string name="z" value="hairBelowBody"/><string name="_hash" value="3fd52777d76aa1cfbf0adadbab88e9c850d870b10d8917969e434bcd54ac9bc0"/></canvas><uol name="hairShade" value="../../default/hairShade"/></imgdir><imgdir name="2"><canvas name="hairOverHead" width="54" height="38"><vector name="origin" x="22" y="20"/><imgdir name="map"><vector name="brow" x="0" y="0"/></imgdir><string name="z" value="hairOverHead"/><string name="_hash" value="81e7f530cd5bebf1bfcce075080f67d4139585bc095c5570d3e2c5ab77fcd604"/></canvas><canvas name="hair" width="41" height="33"><vector name="origin" x="17" y="15"/><imgdir name="map"><vector name="brow" x="0" y="0"/></imgdir><string name="z" value="hair"/><string name="_hash" value="cd76cd3a58f98aab293dbed1b1aa94aa41848e6d5a82688ac1247375b25a5a28"/></canvas><canvas name="hairBelowBody" width="46" height="43"><vector name="origin" x="19" y="15"/><imgdir name="map"><vector name="brow" x="0" y="0"/></imgdir><string name="z" value="hairBelowBody"/><string name="_hash" value="5a05ec64ff78a9952c7aa2a0947b666f3f2565b81c41b08f6d5d4ee2caacbbd8"/></canvas><uol name="hairShade" value="../../default/hairShade"/></imgdir><imgdir name="3"><canvas name="hairOverHead" width="56" height="38"><vector name="origin" x="23" y="20"/><imgdir name="map"><vector name="brow" x="0" y="0"/></imgdir><string name="z" value="hairOverHead"/><string name="_hash" value="869eed0bcd0839bb9754badb8c14e7ec0e7c8e70de680029b3428c4475afcc6e"/></canvas><canvas name="hair" width="1" height="1"><vector name="origin" x="17" y="15"/><imgdir name="map"><vector name="brow" x="0" y="0"/></imgdir><string name="z" value="hair"/><string name="_inlink" value="walk1/1/hair"/></canvas><canvas name="hairBelowBody" width="1" height="1"><vector name="origin" x="19" y="15"/><imgdir name="map"><vector name="brow" x="0" y="0"/></imgdir><string name="z" value="hairBelowBody"/><string name="_inlink" value="walk1/1/hairBelowBody"/></canvas><uol name="hairShade" value="../../default/hairShade"/></imgdir></imgdir><imgdir name="walk2"><imgdir name="0"><uol name="hairOverHead" value="../../walk1/0/hairOverHead"/><uol name="hair" value="../../walk1/0/hair"/><uol name="hairBelowBody" value="../../walk1/0/hairBelowBody"/><uol name="hairShade" value="../../default/hairShade"/></imgdir><imgdir name="1"><uol name="hairOverHead" value="../../walk1/1/hairOverHead"/><uol name="hair" value="../../walk1/1/hair"/><uol name="hairBelowBody" value="../../walk1/1/hairBelowBody"/><uol name="hairShade" value="../../default/hairShade"/></imgdir><imgdir name="2"><uol name="hairOverHead" value="../../walk1/2/hairOverHead"/><uol name="hair" value="../../walk1/2/hair"/><uol name="hairBelowBody" value="../../walk1/2/hairBelowBody"/><uol name="hairShade" value="../../default/hairShade"/></imgdir><imgdir name="3"><uol name="hairOverHead" value="../../walk1/3/hairOverHead"/><uol name="hair" value="../../walk1/3/hair"/><uol name="hairBelowBody" value="../../walk1/3/hairBelowBody"/><uol name="hairShade" value="../../default/hairShade"/></imgdir></imgdir><imgdir name="stand1"><imgdir name="0"><canvas name="hairOverHead" width="1" height="1"><vector name="origin" x="23" y="20"/><imgdir name="map"><vector name="brow" x="0" y="0"/></imgdir><string name="z" value="hairOverHead"/><string name="_inlink" value="walk1/0/hairOverHead"/></canvas><canvas name="hair" width="1" height="1"><vector name="origin" x="17" y="15"/><imgdir name="map"><vector name="brow" x="0" y="0"/></imgdir><string name="z" value="hair"/><string name="_inlink" value="walk1/0/hair"/></canvas><canvas name="hairBelowBody" width="1" height="1"><vector name="origin" x="19" y="15"/><imgdir name="map"><vector name="brow" x="0" y="0"/></imgdir><string name="z" value="hairBelowBody"/><string name="_inlink" value="walk1/0/hairBelowBody"/></canvas><uol name="hairShade" value="../../default/hairShade"/></imgdir><imgdir name="1"><canvas name="hairOverHead" width="1" height="1"><vector name="origin" x="23" y="20"/><imgdir name="map"><vector name="brow" x="0" y="0"/></imgdir><string name="z" value="hairOverHead"/><string name="_inlink" value="walk1/1/hairOverHead"/></canvas><canvas name="hair" width="1" height="1"><vector name="origin" x="17" y="15"/><imgdir name="map"><vector name="brow" x="0" y="0"/></imgdir><string name="z" value="hair"/><string name="_inlink" value="walk1/1/hair"/></canvas><canvas name="hairBelowBody" width="1" height="1"><vector name="origin" x="19" y="15"/><imgdir name="map"><vector name="brow" x="0" y="0"/></imgdir><string name="z" value="hairBelowBody"/><string name="_inlink" value="walk1/1/hairBelowBody"/></canvas><uol name="hairShade" value="../../default/hairShade"/></imgdir><imgdir name="2"><canvas name="hairOverHead" width="1" height="1"><vector name="origin" x="22" y="20"/><imgdir name="map"><vector name="brow" x="0" y="0"/></imgdir><string name="z" value="hairOverHead"/><string name="_inlink" value="walk1/2/hairOverHead"/></canvas><canvas name="hair" width="1" height="1"><vector name="origin" x="17" y="15"/><imgdir name="map"><vector name="brow" x="0" y="0"/></imgdir><string name="z" value="hair"/><string name="_inlink" value="walk1/2/hair"/></canvas><canvas name="hairBelowBody" width="1" height="1"><vector name="origin" x="19" y="15"/><imgdir name="map"><vector name="brow" x="0" y="0"/></imgdir><string name="z" value="hairBelowBody"/><string name="_inlink" value="walk1/2/hairBelowBody"/></canvas><uol name="hairShade" value="../../default/hairShade"/></imgdir></imgdir><imgdir name="stand2"><imgdir name="0"><uol name="hairOverHead" value="../../stand1/0/hairOverHead"/><uol name="hair" value="../../stand1/0/hair"/><uol name="hairBelowBody" value="../../stand1/0/hairBelowBody"/><uol name="hairShade" value="../../default/hairShade"/></imgdir><imgdir name="1"><uol name="hairOverHead" value="../../stand1/1/hairOverHead"/><uol name="hair" value="../../stand1/1/hair"/><uol name="hairBelowBody" value="../../stand1/1/hairBelowBody"/><uol name="hairShade" value="../../default/hairShade"/></imgdir><imgdir name="2"><uol name="hairOverHead" value="../../stand1/2/hairOverHead"/><uol name="hair" value="../../stand1/2/hair"/><uol name="hairBelowBody" value="../../stand1/2/hairBelowBody"/><uol name="hairShade" value="../../default/hairShade"/></imgdir></imgdir><imgdir name="alert"><imgdir name="0"><uol name="hairOverHead" value="../../stand1/0/hairOverHead"/><uol name="hair" value="../../stand1/0/hair"/><uol name="hairBelowBody" value="../../stand1/0/hairBelowBody"/><uol name="hairShade" value="../../default/hairShade"/></imgdir><imgdir name="1"><uol name="hairOverHead" value="../../stand1/1/hairOverHead"/><uol name="hair" value="../../stand1/1/hair"/><uol name="hairBelowBody" value="../../stand1/1/hairBelowBody"/><uol name="hairShade" value="../../default/hairShade"/></imgdir><imgdir name="2"><uol name="hairOverHead" value="../../stand1/2/hairOverHead"/><uol name="hair" value="../../stand1/2/hair"/><uol name="hairBelowBody" value="../../stand1/2/hairBelowBody"/><uol name="hairShade" value="../../default/hairShade"/></imgdir></imgdir><imgdir name="swingO1"><imgdir name="0"><uol name="hairOverHead" value="../../stand1/0/hairOverHead"/><uol name="hair" value="../../stand1/0/hair"/><uol name="hairBelowBody" value="../../stand1/0/hairBelowBody"/><uol name="hairShade" value="../../default/hairShade"/></imgdir><imgdir name="1"><uol name="hairOverHead" value="../../stand1/1/hairOverHead"/><uol name="hair" value="../../stand1/1/hair"/><uol name="hairBelowBody" value="../../stand1/1/hairBelowBody"/><uol name="hairShade" value="../../default/hairShade"/></imgdir><imgdir name="2"><uol name="hairOverHead" value="../../stand1/2/hairOverHead"/><uol name="hair" value="../../stand1/2/hair"/><uol name="hairBelowBody" value="../../stand1/2/hairBelowBody"/><uol name="hairShade" value="../../default/hairShade"/></imgdir></imgdir><imgdir name="swingO2"><imgdir name="0"><uol name="hairOverHead" value="../../stand1/0/hairOverHead"/><uol name="hair" value="../../stand1/0/hair"/><uol name="hairBelowBody" value="../../stand1/0/hairBelowBody"/><uol name="hairShade" value="../../default/hairShade"/></imgdir><imgdir name="1"><uol name="hairOverHead" value="../../stand1/1/hairOverHead"/><uol name="hair" value="../../stand1/1/hair"/><uol name="hairBelowBody" value="../../stand1/1/hairBelowBody"/><uol name="hairShade" value="../../default/hairShade"/></imgdir><imgdir name="2"><uol name="hairOverHead" value="../../stand1/2/hairOverHead"/><uol name="hair" value="../../stand1/2/hair"/><uol name="hairBelowBody" value="../../stand1/2/hairBelowBody"/><uol name="hairShade" value="../../default/hairShade"/></imgdir></imgdir><imgdir name="swingO3"><imgdir name="0"><uol name="hairOverHead" value="../../stand1/0/hairOverHead"/><uol name="hair" value="../../stand1/0/hair"/><uol name="hairBelowBody" value="../../stand1/0/hairBelowBody"/><uol name="hairShade" value="../../default/hairShade"/></imgdir><imgdir name="1"><uol name="hairOverHead" value="../../stand1/1/hairOverHead"/><uol name="hair" value="../../stand1/1/hair"/><uol name="hairBelowBody" value="../../stand1/1/hairBelowBody"/><uol name="hairShade" value="../../default/hairShade"/></imgdir><imgdir name="2"><uol name="hairOverHead" value="../../stand1/2/hairOverHead"/><uol name="hair" value="../../stand1/2/hair"/><uol name="hairBelowBody" value="../../stand1/2/hairBelowBody"/><uol name="hairShade" value="../../default/hairShade"/></imgdir></imgdir><imgdir name="swingOF"><imgdir name="0"><uol name="hairOverHead" value="../../stand1/1/hairOverHead"/><uol name="hair" value="../../stand1/1/hair"/><uol name="hairBelowBody" value="../../stand1/1/hairBelowBody"/><uol name="hairShade" value="../../default/hairShade"/></imgdir><imgdir name="1"><uol name="backHair" value="../../ladder/0/backHair"/><uol name="backHairBelowCap" value="../../ladder/0/backHairBelowCap"/></imgdir><imgdir name="2"><uol name="hairOverHead" value="../../stand1/1/hairOverHead"/><uol name="hair" value="../../stand1/1/hair"/><uol name="hairBelowBody" value="../../stand1/1/hairBelowBody"/><uol name="hairShade" value="../../default/hairShade"/></imgdir><imgdir name="3"><uol name="hairOverHead" value="../../stand1/0/hairOverHead"/><uol name="hair" value="../../stand1/0/hair"/><uol name="hairBelowBody" value="../../stand1/0/hairBelowBody"/><uol name="hairShade" value="../../default/hairShade"/></imgdir></imgdir><imgdir name="swingT1"><imgdir name="0"><uol name="hairOverHead" value="../../stand1/0/hairOverHead"/><uol name="hair" value="../../stand1/0/hair"/><uol name="hairBelowBody" value="../../stand1/0/hairBelowBody"/><uol name="hairShade" value="../../default/hairShade"/></imgdir><imgdir name="1"><uol name="hairOverHead" value="../../stand1/1/hairOverHead"/><uol name="hair" value="../../stand1/1/hair"/><uol name="hairBelowBody" value="../../stand1/1/hairBelowBody"/><uol name="hairShade" value="../../default/hairShade"/></imgdir><imgdir name="2"><uol name="hairOverHead" value="../../stand1/2/hairOverHead"/><uol name="hair" value="../../stand1/2/hair"/><uol name="hairBelowBody" value="../../stand1/2/hairBelowBody"/><uol name="hairShade" value="../../default/hairShade"/></imgdir></imgdir><imgdir name="swingT2"><imgdir name="0"><uol name="hairOverHead" value="../../stand1/0/hairOverHead"/><uol name="hair" value="../../stand1/0/hair"/><uol name="hairBelowBody" value="../../stand1/0/hairBelowBody"/><uol name="hairShade" value="../../default/hairShade"/></imgdir><imgdir name="1"><uol name="hairOverHead" value="../../stand1/1/hairOverHead"/><uol name="hair" value="../../stand1/1/hair"/><uol name="hairBelowBody" value="../../stand1/1/hairBelowBody"/><uol name="hairShade" value="../../default/hairShade"/></imgdir><imgdir name="2"><uol name="hairOverHead" value="../../stand1/2/hairOverHead"/><uol name="hair" value="../../stand1/2/hair"/><uol name="hairBelowBody" value="../../stand1/2/hairBelowBody"/><uol name="hairShade" value="../../default/hairShade"/></imgdir></imgdir><imgdir name="swingT3"><imgdir name="0"><uol name="hairOverHead" value="../../stand1/0/hairOverHead"/><uol name="hair" value="../../stand1/0/hair"/><uol name="hairBelowBody" value="../../stand1/0/hairBelowBody"/><uol name="hairShade" value="../../default/hairShade"/></imgdir><imgdir name="1"><uol name="hairOverHead" value="../../stand1/1/hairOverHead"/><uol name="hair" value="../../stand1/1/hair"/><uol name="hairBelowBody" value="../../stand1/1/hairBelowBody"/><uol name="hairShade" value="../../default/hairShade"/></imgdir><imgdir name="2"><uol name="hairOverHead" value="../../stand1/2/hairOverHead"/><uol name="hair" value="../../stand1/2/hair"/><uol name="hairBelowBody" value="../../stand1/2/hairBelowBody"/><uol name="hairShade" value="../../default/hairShade"/></imgdir></imgdir><imgdir name="swingTF"><imgdir name="0"><uol name="backHair" value="../../ladder/0/backHair"/><uol name="backHairBelowCap" value="../../ladder/0/backHairBelowCap"/></imgdir><imgdir name="1"><uol name="hairOverHead" value="../../stand1/2/hairOverHead"/><uol name="hair" value="../../stand1/2/hair"/><uol name="hairBelowBody" value="../../stand1/2/hairBelowBody"/><uol name="hairShade" value="../../default/hairShade"/></imgdir><imgdir name="2"><uol name="hairOverHead" value="../../stand1/1/hairOverHead"/><uol name="hair" value="../../stand1/1/hair"/><uol name="hairBelowBody" value="../../stand1/1/hairBelowBody"/><uol name="hairShade" value="../../default/hairShade"/></imgdir><imgdir name="3"><uol name="hairOverHead" value="../../stand1/0/hairOverHead"/><uol name="hair" value="../../stand1/0/hair"/><uol name="hairBelowBody" value="../../stand1/0/hairBelowBody"/><uol name="hairShade" value="../../default/hairShade"/></imgdir></imgdir><imgdir name="swingP1"><imgdir name="0"><uol name="hairOverHead" value="../../stand1/0/hairOverHead"/><uol name="hair" value="../../stand1/0/hair"/><uol name="hairBelowBody" value="../../stand1/0/hairBelowBody"/><uol name="hairShade" value="../../default/hairShade"/></imgdir><imgdir name="1"><uol name="hairOverHead" value="../../stand1/1/hairOverHead"/><uol name="hair" value="../../stand1/1/hair"/><uol name="hairBelowBody" value="../../stand1/1/hairBelowBody"/><uol name="hairShade" value="../../default/hairShade"/></imgdir><imgdir name="2"><uol name="hairOverHead" value="../../stand1/2/hairOverHead"/><uol name="hair" value="../../stand1/2/hair"/><uol name="hairBelowBody" value="../../stand1/2/hairBelowBody"/><uol name="hairShade" value="../../default/hairShade"/></imgdir></imgdir><imgdir name="swingP2"><imgdir name="0"><uol name="hairOverHead" value="../../stand1/0/hairOverHead"/><uol name="hair" value="../../stand1/0/hair"/><uol name="hairBelowBody" value="../../stand1/0/hairBelowBody"/><uol name="hairShade" value="../../default/hairShade"/></imgdir><imgdir name="1"><uol name="hairOverHead" value="../../stand1/1/hairOverHead"/><uol name="hair" value="../../stand1/1/hair"/><uol name="hairBelowBody" value="../../stand1/1/hairBelowBody"/><uol name="hairShade" value="../../default/hairShade"/></imgdir><imgdir name="2"><uol name="hairOverHead" value="../../stand1/2/hairOverHead"/><uol name="hair" value="../../stand1/2/hair"/><uol name="hairBelowBody" value="../../stand1/2/hairBelowBody"/><uol name="hairShade" value="../../default/hairShade"/></imgdir></imgdir><imgdir name="swingPF"><imgdir name="0"><uol name="hairOverHead" value="../../stand1/1/hairOverHead"/><uol name="hair" value="../../stand1/1/hair"/><uol name="hairBelowBody" value="../../stand1/1/hairBelowBody"/><uol name="hairShade" value="../../default/hairShade"/></imgdir><imgdir name="1"><uol name="hairOverHead" value="../../stand1/2/hairOverHead"/><uol name="hair" value="../../stand1/2/hair"/><uol name="hairBelowBody" value="../../stand1/2/hairBelowBody"/><uol name="hairShade" value="../../default/hairShade"/></imgdir><imgdir name="2"><uol name="hairOverHead" value="../../stand1/1/hairOverHead"/><uol name="hair" value="../../stand1/1/hair"/><uol name="hairBelowBody" value="../../stand1/1/hairBelowBody"/><uol name="hairShade" value="../../default/hairShade"/></imgdir><imgdir name="3"><uol name="hairOverHead" value="../../stand1/0/hairOverHead"/><uol name="hair" value="../../stand1/0/hair"/><uol name="hairBelowBody" value="../../stand1/0/hairBelowBody"/><uol name="hairShade" value="../../default/hairShade"/></imgdir></imgdir><imgdir name="stabO1"><imgdir name="0"><uol name="hairOverHead" value="../../stand1/0/hairOverHead"/><uol name="hair" value="../../stand1/0/hair"/><uol name="hairBelowBody" value="../../stand1/0/hairBelowBody"/><uol name="hairShade" value="../../default/hairShade"/></imgdir><imgdir name="1"><uol name="hairOverHead" value="../../stand1/0/hairOverHead"/><uol name="hair" value="../../stand1/0/hair"/><uol name="hairBelowBody" value="../../stand1/0/hairBelowBody"/><uol name="hairShade" value="../../default/hairShade"/></imgdir></imgdir><imgdir name="stabO2"><imgdir name="0"><uol name="hairOverHead" value="../../stand1/0/hairOverHead"/><uol name="hair" value="../../stand1/0/hair"/><uol name="hairBelowBody" value="../../stand1/0/hairBelowBody"/><uol name="hairShade" value="../../default/hairShade"/></imgdir><imgdir name="1"><uol name="hairOverHead" value="../../stand1/0/hairOverHead"/><uol name="hair" value="../../stand1/0/hair"/><uol name="hairBelowBody" value="../../stand1/0/hairBelowBody"/><uol name="hairShade" value="../../default/hairShade"/></imgdir></imgdir><imgdir name="stabOF"><imgdir name="0"><uol name="hairOverHead" value="../../stand1/0/hairOverHead"/><uol name="hair" value="../../stand1/0/hair"/><uol name="hairBelowBody" value="../../stand1/0/hairBelowBody"/><uol name="hairShade" value="../../default/hairShade"/></imgdir><imgdir name="1"><uol name="hairOverHead" value="../../stand1/1/hairOverHead"/><uol name="hair" value="../../stand1/1/hair"/><uol name="hairBelowBody" value="../../stand1/1/hairBelowBody"/><uol name="hairShade" value="../../default/hairShade"/></imgdir><imgdir name="2"><uol name="hairOverHead" value="../../stand1/2/hairOverHead"/><uol name="hair" value="../../stand1/2/hair"/><uol name="hairBelowBody" value="../../stand1/2/hairBelowBody"/><uol name="hairShade" value="../../default/hairShade"/></imgdir></imgdir><imgdir name="stabT1"><imgdir name="0"><uol name="hairOverHead" value="../../stand1/0/hairOverHead"/><uol name="hair" value="../../stand1/0/hair"/><uol name="hairBelowBody" value="../../stand1/0/hairBelowBody"/><uol name="hairShade" value="../../default/hairShade"/></imgdir><imgdir name="1"><uol name="hairOverHead" value="../../stand1/1/hairOverHead"/><uol name="hair" value="../../stand1/1/hair"/><uol name="hairBelowBody" value="../../stand1/1/hairBelowBody"/><uol name="hairShade" value="../../default/hairShade"/></imgdir><imgdir name="2"><uol name="hairOverHead" value="../../stand1/2/hairOverHead"/><uol name="hair" value="../../stand1/2/hair"/><uol name="hairBelowBody" value="../../stand1/2/hairBelowBody"/><uol name="hairShade" value="../../default/hairShade"/></imgdir></imgdir><imgdir name="stabT2"><imgdir name="0"><uol name="hairOverHead" value="../../stand1/0/hairOverHead"/><uol name="hair" value="../../stand1/0/hair"/><uol name="hairBelowBody" value="../../stand1/0/hairBelowBody"/><uol name="hairShade" value="../../default/hairShade"/></imgdir><imgdir name="1"><uol name="hairOverHead" value="../../stand1/1/hairOverHead"/><uol name="hair" value="../../stand1/1/hair"/><uol name="hairBelowBody" value="../../stand1/1/hairBelowBody"/><uol name="hairShade" value="../../default/hairShade"/></imgdir><imgdir name="2"><uol name="hairOverHead" value="../../stand1/2/hairOverHead"/><uol name="hair" value="../../stand1/2/hair"/><uol name="hairBelowBody" value="../../stand1/2/hairBelowBody"/><uol name="hairShade" value="../../default/hairShade"/></imgdir></imgdir><imgdir name="stabTF"><imgdir name="0"><uol name="hairOverHead" value="../../stand1/1/hairOverHead"/><uol name="hair" value="../../stand1/1/hair"/><uol name="hairBelowBody" value="../../stand1/1/hairBelowBody"/><uol name="hairShade" value="../../default/hairShade"/></imgdir><imgdir name="1"><uol name="hairOverHead" value="../../stand1/2/hairOverHead"/><uol name="hair" value="../../stand1/2/hair"/><uol name="hairBelowBody" value="../../stand1/2/hairBelowBody"/><uol name="hairShade" value="../../default/hairShade"/></imgdir><imgdir name="2"><uol name="hairOverHead" value="../../stand1/1/hairOverHead"/><uol name="hair" value="../../stand1/1/hair"/><uol name="hairBelowBody" value="../../stand1/1/hairBelowBody"/><uol name="hairShade" value="../../default/hairShade"/></imgdir><imgdir name="3"><uol name="hairOverHead" value="../../stand1/0/hairOverHead"/><uol name="hair" value="../../stand1/0/hair"/><uol name="hairBelowBody" value="../../stand1/0/hairBelowBody"/><uol name="hairShade" value="../../default/hairShade"/></imgdir></imgdir><imgdir name="shoot1"><imgdir name="0"><uol name="hairOverHead" value="../../stand1/0/hairOverHead"/><uol name="hair" value="../../stand1/0/hair"/><uol name="hairBelowBody" value="../../stand1/0/hairBelowBody"/><uol name="hairShade" value="../../default/hairShade"/></imgdir><imgdir name="1"><uol name="hairOverHead" value="../../stand1/1/hairOverHead"/><uol name="hair" value="../../stand1/1/hair"/><uol name="hairBelowBody" value="../../stand1/1/hairBelowBody"/><uol name="hairShade" value="../../default/hairShade"/></imgdir><imgdir name="2"><uol name="hairOverHead" value="../../stand1/2/hairOverHead"/><uol name="hair" value="../../stand1/2/hair"/><uol name="hairBelowBody" value="../../stand1/2/hairBelowBody"/><uol name="hairShade" value="../../default/hairShade"/></imgdir></imgdir><imgdir name="shoot2"><imgdir name="0"><uol name="hairOverHead" value="../../stand1/0/hairOverHead"/><uol name="hair" value="../../stand1/0/hair"/><uol name="hairBelowBody" value="../../stand1/0/hairBelowBody"/><uol name="hairShade" value="../../default/hairShade"/></imgdir><imgdir name="1"><uol name="hairOverHead" value="../../stand1/0/hairOverHead"/><uol name="hair" value="../../stand1/0/hair"/><uol name="hairBelowBody" value="../../stand1/0/hairBelowBody"/><uol name="hairShade" value="../../default/hairShade"/></imgdir><imgdir name="2"><uol name="hairOverHead" value="../../stand1/0/hairOverHead"/><uol name="hair" value="../../stand1/0/hair"/><uol name="hairBelowBody" value="../../stand1/0/hairBelowBody"/><uol name="hairShade" value="../../default/hairShade"/></imgdir><imgdir name="3"><uol name="hairOverHead" value="../../stand1/0/hairOverHead"/><uol name="hair" value="../../stand1/0/hair"/><uol name="hairBelowBody" value="../../stand1/0/hairBelowBody"/><uol name="hairShade" value="../../default/hairShade"/></imgdir><imgdir name="4"><uol name="hairOverHead" value="../../stand1/0/hairOverHead"/><uol name="hair" value="../../stand1/0/hair"/><uol name="hairBelowBody" value="../../stand1/0/hairBelowBody"/><uol name="hairShade" value="../../default/hairShade"/></imgdir></imgdir><imgdir name="shootF"><imgdir name="0"><uol name="hairOverHead" value="../../stand1/0/hairOverHead"/><uol name="hair" value="../../stand1/0/hair"/><uol name="hairBelowBody" value="../../stand1/0/hairBelowBody"/><uol name="hairShade" value="../../default/hairShade"/></imgdir><imgdir name="1"><uol name="hairOverHead" value="../../stand1/1/hairOverHead"/><uol name="hair" value="../../stand1/1/hair"/><uol name="hairBelowBody" value="../../stand1/1/hairBelowBody"/><uol name="hairShade" value="../../default/hairShade"/></imgdir><imgdir name="2"><uol name="hairOverHead" value="../../stand1/2/hairOverHead"/><uol name="hair" value="../../stand1/2/hair"/><uol name="hairBelowBody" value="../../stand1/2/hairBelowBody"/><uol name="hairShade" value="../../default/hairShade"/></imgdir></imgdir><imgdir name="proneStab"><imgdir name="0"><canvas name="hairOverHead" width="55" height="38"><vector name="origin" x="23" y="20"/><imgdir name="map"><vector name="brow" x="0" y="0"/></imgdir><string name="z" value="hairOverHead"/><string name="_hash" value="ceeaad9c79b85fbc4c7999d48440e452f1aa0247187d0aa62b66b61cba4bbc7c"/></canvas><canvas name="hair" width="1" height="1"><vector name="origin" x="17" y="15"/><imgdir name="map"><vector name="brow" x="0" y="0"/></imgdir><string name="z" value="hair"/><string name="_inlink" value="walk1/1/hair"/></canvas><canvas name="hairBelowBody" width="46" height="41"><vector name="origin" x="19" y="15"/><imgdir name="map"><vector name="brow" x="0" y="0"/></imgdir><string name="z" value="hairBelowBody"/><string name="_hash" value="be5f304176a2980e5bbd3d57d8e731478edd7110283b707079bc027a4a05ce2d"/></canvas><uol name="hairShade" value="../../default/hairShade"/></imgdir><imgdir name="1"><canvas name="hairOverHead" width="56" height="38"><vector name="origin" x="23" y="20"/><imgdir name="map"><vector name="brow" x="0" y="0"/></imgdir><string name="z" value="hairOverHead"/><string name="_hash" value="118b9d4154b94ca0cba191c221083fad23083a94b7bff4a35c04fd9c4b7852f8"/></canvas><canvas name="hair" width="1" height="1"><vector name="origin" x="17" y="15"/><imgdir name="map"><vector name="brow" x="0" y="0"/></imgdir><string name="z" value="hair"/><string name="_inlink" value="walk1/1/hair"/></canvas><canvas name="hairBelowBody" width="46" height="42"><vector name="origin" x="19" y="15"/><imgdir name="map"><vector name="brow" x="0" y="0"/></imgdir><string name="z" value="hairBelowBody"/><string name="_hash" value="6b08abfd541c7cc4468cb3b764f3d04a441a9c34cae3db923b67a57051f6fff2"/></canvas><uol name="hairShade" value="../../default/hairShade"/></imgdir></imgdir><imgdir name="prone"><imgdir name="0"><uol name="hairOverHead" value="../../proneStab/0/hairOverHead"/><uol name="hair" value="../../proneStab/0/hair"/><uol name="hairBelowBody" value="../../proneStab/0/hairBelowBody"/><uol name="hairShade" value="../../default/hairShade"/></imgdir></imgdir><imgdir name="heal"><imgdir name="0"><uol name="hairOverHead" value="../../stand1/0/hairOverHead"/><uol name="hair" value="../../stand1/0/hair"/><uol name="hairBelowBody" value="../../stand1/0/hairBelowBody"/><uol name="hairShade" value="../../default/hairShade"/></imgdir><imgdir name="1"><uol name="hairOverHead" value="../../stand1/1/hairOverHead"/><uol name="hair" value="../../stand1/1/hair"/><uol name="hairBelowBody" value="../../stand1/1/hairBelowBody"/><uol name="hairShade" value="../../default/hairShade"/></imgdir><imgdir name="2"><uol name="hairOverHead" value="../../stand1/2/hairOverHead"/><uol name="hair" value="../../stand1/2/hair"/><uol name="hairBelowBody" value="../../stand1/2/hairBelowBody"/><uol name="hairShade" value="../../default/hairShade"/></imgdir></imgdir><imgdir name="fly"><imgdir name="0"><uol name="hairOverHead" value="../../stand1/0/hairOverHead"/><uol name="hair" value="../../stand1/0/hair"/><uol name="hairBelowBody" value="../../stand1/0/hairBelowBody"/><uol name="hairShade" value="../../default/hairShade"/></imgdir><imgdir name="1"><uol name="hairOverHead" value="../../stand1/0/hairOverHead"/><uol name="hair" value="../../stand1/0/hair"/><uol name="hairBelowBody" value="../../stand1/0/hairBelowBody"/><uol name="hairShade" value="../../default/hairShade"/></imgdir></imgdir><imgdir name="jump"><imgdir name="0"><uol name="hairOverHead" value="../../stand1/1/hairOverHead"/><uol name="hair" value="../../stand1/1/hair"/><uol name="hairBelowBody" value="../../stand1/1/hairBelowBody"/><uol name="hairShade" value="../../default/hairShade"/></imgdir></imgdir><imgdir name="sit"><imgdir name="0"><uol name="hairOverHead" value="../../stand1/0/hairOverHead"/><uol name="hair" value="../../stand1/0/hair"/><uol name="hairBelowBody" value="../../stand1/0/hairBelowBody"/><uol name="hairShade" value="../../default/hairShade"/></imgdir></imgdir><imgdir name="ladder"><imgdir name="0"><canvas name="backHair" width="54" height="45"><vector name="origin" x="22" y="20"/><imgdir name="map"><vector name="brow" x="0" y="0"/></imgdir><string name="z" value="backHair"/><string name="_hash" value="2b49fc1cf0d3ec492e2ad8e20c8be15b83e65f18ecf11c5782df823963cfd79a"/></canvas><canvas name="backHairBelowCap" width="41" height="41"><vector name="origin" x="16" y="15"/><imgdir name="map"><vector name="brow" x="0" y="0"/></imgdir><string name="z" value="backHairBelowCap"/><string name="_hash" value="b6d28dfeacc30f45854fa5331f380aabd6b042826264b53ab2059c551d6edb1a"/></canvas></imgdir><imgdir name="1"><canvas name="backHair" width="53" height="45"><vector name="origin" x="22" y="20"/><imgdir name="map"><vector name="brow" x="0" y="0"/></imgdir><string name="z" value="backHair"/><string name="_hash" value="586e904193727fdd2d77e2d22671abbf3c131bc4f168a5dbcb6839a862d64b18"/></canvas><canvas name="backHairBelowCap" width="41" height="41"><vector name="origin" x="16" y="15"/><imgdir name="map"><vector name="brow" x="0" y="0"/></imgdir><string name="z" value="backHairBelowCap"/><string name="_hash" value="74961158a14125a77607b6f621e965198e7d7ad085559847688ba8f134bc918a"/></canvas></imgdir></imgdir><imgdir name="rope"><imgdir name="0"><uol name="backHair" value="../../ladder/0/backHair"/><uol name="backHairBelowCap" value="../../ladder/0/backHairBelowCap"/></imgdir><imgdir name="1"><uol name="backHair" value="../../ladder/1/backHair"/><uol name="backHairBelowCap" value="../../ladder/1/backHairBelowCap"/></imgdir></imgdir></imgdir>